{
  "retrieval_debug_id": "64b72b02-03af-42e8-93db-68e27beacac6",
  "run_id": "b7d0e452-2555-45dd-b8c2-c4c979b63015",
  "timestamp": "2026-06-06T11:50:41.794Z",
  "included_sources": [
    {
      "path": "E:\\武裝學院的二三事\\data\\canon_db\\active_engine.md",
      "reason": "canon"
    },
    {
      "path": "E:\\武裝學院的二三事\\data\\writing_policy_db\\active_writing_card.md",
      "reason": "writing_card"
    },
    {
      "path": "E:\\武裝學院的二三事\\data\\error_report_db\\compressed_rules.md",
      "reason": "error_rules"
    },
    {
      "path": "E:\\武裝學院的二三事\\data\\error_report_db\\battle_errors.jsonl",
      "reason": "error_report"
    },
    {
      "path": "E:\\武裝學院的二三事\\data\\error_report_db\\canon_errors.jsonl",
      "reason": "error_report"
    },
    {
      "path": "E:\\武裝學院的二三事\\data\\error_report_db\\character_errors.jsonl",
      "reason": "error_report"
    },
    {
      "path": "E:\\武裝學院的二三事\\data\\error_report_db\\dialogue_errors.jsonl",
      "reason": "error_report"
    },
    {
      "path": "E:\\武裝學院的二三事\\data\\error_report_db\\pacing_errors.jsonl",
      "reason": "error_report"
    }
  ],
  "final_context_status": "usable"
}